spalb/U_GA.py
spalb/__init__.py
spalb/straight.py
spalb-1.6.1.dist-info/LICENSE.txt
spalb-1.6.1.dist-info/METADATA
spalb-1.6.1.dist-info/WHEEL
spalb-1.6.1.dist-info/top_level.txt
spalb-1.6.1.dist-info/RECORD
