Metadata-Version: 2.1
Name: spalb
Version: 1.6.1
Summary: This package can solve single product assembly line balancing problem
Home-page: UNKNOWN
Author: Sirapob and Siriwimon 
Author-email: 16630.mnr@gmail.com
License: UNKNOWN
Project-URL: Documentation, https://spalb.github.io/documentation/
Platform: UNKNOWN
Classifier: Programming Language :: Python :: 3
Classifier: License :: OSI Approved :: GNU Lesser General Public License v3 or later (LGPLv3+)
Classifier: Operating System :: OS Independent
Requires-Python: >=3.7
License-File: LICENSE.txt
